AstraCarta/AstraCarta.py
AstraCarta/__init__.py
AstraCarta-1.0.39.dist-info/LICENSE
AstraCarta-1.0.39.dist-info/METADATA
AstraCarta-1.0.39.dist-info/WHEEL
AstraCarta-1.0.39.dist-info/entry_points.txt
AstraCarta-1.0.39.dist-info/top_level.txt
AstraCarta-1.0.39.dist-info/RECORD
