Metadata-Version: 2.1
Name: AstraCarta
Version: 1.0.39
Summary: Perform astroquery with useful options
Home-page: https://github.com/user29A/astracarta
Author: Joseph E. Postma
Author-email: joepostma@live.ca, jpostma@ucalgary.ca
Project-URL: Bug Tracker, https://github.com/user29A/astracarta/issues
Classifier: Programming Language :: Python :: 3
Classifier: License :: OSI Approved :: MIT License
Classifier: Operating System :: OS Independent
Requires-Python: >=3.10
License-File: LICENSE
Requires-Dist: astroquery (>=0.4.6)
Requires-Dist: matplotlib (>=3.5.0)
